unqlite.cpython-311-x86_64-linux-gnu.so
unqlite-1.0.0.dist-info/METADATA
unqlite-1.0.0.dist-info/WHEEL
unqlite-1.0.0.dist-info/top_level.txt
unqlite-1.0.0.dist-info/RECORD
unqlite-1.0.0.dist-info/licenses/LICENSE
