Metadata-Version: 2.4
Name: unqlite
Version: 1.0.0
Summary: fast bindings for the unqlite embedded database
Author-email: Charles Leifer <coleifer@gmail.com>
Project-URL: Repository, https://github.com/coleifer/unqlite-python
Project-URL: Documentation, https://unqlite-python.readthedocs.io/
Classifier: Programming Language :: Python :: 2
Classifier: Programming Language :: Python :: 3
Classifier: Topic :: Database :: Database Engines/Servers
Classifier: Topic :: Software Development :: Embedded Systems
Classifier: Topic :: Software Development :: Libraries :: Python Modules
License-File: LICENSE
Dynamic: license-file
